{
  "description": "This dataset contains demographic variables gathered from the American Community Survey (ACS) from 2018 to 2022. It includes data related language and population diversity",
  "source": "American Community Survey (ACS) - US Census Bureau",
  "geography": {
    "level": "Census Tract",
    "geoid_description": "11-digit GEOID representing census tract.",
    "geoid_components": {
      "state_GEOID": "First 2 digits",
      "county_GEOID": "Next 3 digits",
      "tract_GEOID": "Last 6 digits"
    }
  },
  "variables": [
    {
      "name": "population",
      "description": "Total Population",
      "type": "float",
      "units": "Population in Census Tract",
      "source_notes": "ACS variable code DP05_0001E"
    },

    {
      "name": "foreign_born_p",
      "description": "Percent of foreign born population",
      "type": "float",
      "units": "Percent out of total geography population",
      "source_notes": "ACS variable code DP02_0094PE"
    },

    {
      "name": "no_english_p",
      "description": "Population 5 and over who speak English less than 'very well'",
      "type": "float",
      "units": "Percent out of total geography population",
      "source_notes": "ACS variable code DP02_0115PE"
    }
    
  ],
  "update_frequency": "Yearly (5-year estimates)",
  "notes": [
    "GEOIDs correspond to Census tracts for the given year of the dataset. Note that Census tract boundaries have changed after the 2020 decennial census, which may affect geographic consistency over time."
  ]
}